functional_dependencies/__init__.py
functional_dependencies/functional_dependencies.py
functional_dependencies-1.3.0.dist-info/CC-BY-4.0.txt
functional_dependencies-1.3.0.dist-info/CC0-1.0.txt
functional_dependencies-1.3.0.dist-info/GPL-3.0-or-later.txt
functional_dependencies-1.3.0.dist-info/LICENSE
functional_dependencies-1.3.0.dist-info/METADATA
functional_dependencies-1.3.0.dist-info/WHEEL
functional_dependencies-1.3.0.dist-info/top_level.txt
functional_dependencies-1.3.0.dist-info/RECORD
