Metadata-Version: 2.1
Name: functional-dependencies
Version: 1.3.0
Summary: Compute functional dependencies for database schema design and normalization: implication, closure, synthesis
Home-page: https://gitlab.com/oer/cs/functional-dependencies
Author: Jens Lechtenbörger
Author-email: lechten@wi.uni-muenster.de
License: GPL-3.0-or-later AND CC0-1.0 AND CC-BY-4.0
Project-URL: Documentation, https://oer.gitlab.io/cs/functional-dependencies/
Platform: UNKNOWN
Classifier: Programming Language :: Python
Classifier: Programming Language :: Python :: 2.7
Classifier: Programming Language :: Python :: 3
Classifier: Intended Audience :: Education
Classifier: Intended Audience :: Information Technology
Classifier: License :: OSI Approved :: GNU General Public License v3 or later (GPLv3+)
Classifier: License :: CC0 1.0 Universal (CC0 1.0) Public Domain Dedication
Classifier: Topic :: Database
Classifier: Topic :: Education
